{
  "questions": [
    {
      "isTemplate": true,
      "variables": {
        "num_cities": {
          "min": 5,
          "max": 12,
          "step": 1
        }
      },
      "constraints": [
        "num_cities >= 3"
      ],
      "formulas": {
        "ans": "num_cities * (num_cities - 1) / 2",
        "w1": "num_cities * 2",
        "w2": "num_cities * num_cities",
        "w3": "num_cities + (num_cities - 1)"
      },
      "questionText": "Trên một tuyến đường sắt thẳng, người ta xây dựng {num_cities} nhà ga phân biệt. Mỗi đoạn đường thẳng nối hai nhà ga bất kì được xem là một 'tuyến con'. Hỏi có tất cả bao nhiêu 'tuyến con' như vậy?",
      "options": [
        "A. {w1} tuyến con",
        "B. {ans} tuyến con",
        "C. {w2} tuyến con",
        "D. {w3} tuyến con"
      ],
      "correctIndex": 1,
      "hints": [
        "Đây là bài toán đếm số đoạn thẳng được tạo bởi {num_cities} điểm phân biệt trên một đường thẳng.",
        "Công thức tính số đoạn thẳng từ $n$ điểm phân biệt trên một đường thẳng là $\\frac{n(n-1)}{2}$."
      ],
      "solutionHtml": "Số tuyến con được tạo bởi {num_cities} nhà ga (tức là {num_cities} điểm phân biệt trên đường thẳng) là:<br/>$ \\frac{{num_cities} \\times ({num_cities} - 1)}{2} = \\frac{{num_cities * (num_cities - 1)}}{2} = {ans} $ (tuyến con).<br/>Vậy có tất cả {ans} tuyến con.<br/>Đáp án đúng là B.",
      "tip": "Mỗi đoạn thẳng được xác định bởi hai điểm. Thứ tự các điểm không quan trọng. Đây là công thức tổ hợp $C_n^2$."
    },
    {
      "isTemplate": true,
      "variables": {
        "dist_AB": {
          "min": 10,
          "max": 50,
          "step": 5
        },
        "dist_BC": {
          "min": 10,
          "max": 50,
          "step": 5
        }
      },
      "constraints": [
        "dist_AB !== dist_BC"
      ],
      "formulas": {
        "dist_AC_true": "dist_AB + dist_BC",
        "dist_AC_fake1": "Math.abs(dist_AB - dist_BC)",
        "ans_statement": "'Điểm B nằm giữa hai điểm A và C.'",
        "w1_statement": "'Điểm A nằm giữa hai điểm B và C.'",
        "w2_statement": "'Điểm C nằm giữa hai điểm A và B.'",
        "w3_statement": "'Ba điểm A, B, C không thẳng hàng.'"
      },
      "questionText": "Ba trạm phát sóng A, B, C được đặt trên một đường thẳng. Người ta đo được khoảng cách giữa các trạm là: $AB = {dist_AB}$ km, $BC = {dist_BC}$ km, và $AC = {dist_AC_true}$ km. Dựa vào các thông số này, khẳng định nào sau đây là đúng?",
      "options": [
        "A. {w1_statement}",
        "B. {ans_statement}",
        "C. {w2_statement}",
        "D. {w3_statement}"
      ],
      "correctIndex": 1,
      "hints": [
        "Nhớ lại định nghĩa điểm nằm giữa hai điểm dựa trên độ dài đoạn thẳng.",
        "Nếu điểm M nằm giữa hai điểm P và Q, thì $PM + MQ = PQ$."
      ],
      "solutionHtml": "Ta có các khoảng cách đã cho là: $AB = {dist_AB}$ km, $BC = {dist_BC}$ km, $AC = {dist_AC_true}$ km.<br/>Để xác định điểm nào nằm giữa hai điểm còn lại, ta kiểm tra tổng độ dài của hai đoạn thẳng nhỏ có bằng độ dài đoạn thẳng lớn nhất hay không.<br/>Ta thấy: $AB + BC = {dist_AB} + {dist_BC} = {dist_AC_true}$ km.<br/>Mà $AC = {dist_AC_true}$ km.<br/>Vì $AB + BC = AC$, theo định nghĩa điểm nằm giữa hai điểm, điểm B phải nằm giữa hai điểm A và C.<br/>Đáp án đúng là B.",
      "tip": "Khi ba điểm A, B, C thẳng hàng, nếu $AB + BC = AC$ thì B nằm giữa A và C. Nếu $AB + AC = BC$ thì A nằm giữa B và C. Nếu $BC + AC = AB$ thì C nằm giữa A và B. Nếu không có tổng nào bằng nhau thì ba điểm không thẳng hàng."
    },
    {
      "isTemplate": true,
      "variables": {
        "len_AB": {
          "min": 15,
          "max": 60,
          "step": 5
        },
        "len_BC": {
          "min": 10,
          "max": 40,
          "step": 5
        }
      },
      "constraints": [],
      "formulas": {
        "ans": "len_AB + len_BC",
        "w1": "Math.abs(len_AB - len_BC)",
        "w2": "len_AB * len_BC",
        "w3": "len_AB + len_BC + 10"
      },
      "questionText": "Một tuyến xe buýt chạy thẳng qua ba điểm dừng A, B, C. Biết rằng điểm dừng B nằm giữa điểm dừng A và điểm dừng C. Khoảng cách từ A đến B là {len_AB} km và từ B đến C là {len_BC} km. Hỏi tổng quãng đường từ A đến C là bao nhiêu km?",
      "options": [
        "A. {w1} km",
        "B. {ans} km",
        "C. {w2} km",
        "D. {w3} km"
      ],
      "correctIndex": 1,
      "hints": [
        "Khi điểm B nằm giữa A và C, độ dài đoạn thẳng AC bằng tổng độ dài đoạn thẳng AB và BC.",
        "Thực hiện phép cộng {len_AB} + {len_BC}$."
      ],
      "solutionHtml": "Vì điểm B nằm giữa điểm A và điểm C, nên ta có đẳng thức về độ dài đoạn thẳng:<br/>$AC = AB + BC$<br/>Thay số vào, ta được:<br/>$AC = {len_AB} + {len_BC} = {ans}$ km.<br/>Vậy tổng quãng đường từ A đến C là {ans} km.<br/>Đáp án đúng là B.",
      "tip": "Lời giải rất rõ ràng từ định nghĩa điểm nằm giữa hai điểm. Quan trọng là xác định đúng mối quan hệ giữa các điểm."
    },
    {
      "isTemplate": true,
      "variables": {
        "len_MN": {
          "min": 50,
          "max": 100,
          "step": 10
        },
        "len_MP": {
          "min": 10,
          "max": 40,
          "step": 5
        }
      },
      "constraints": [
        "len_MN > len_MP"
      ],
      "formulas": {
        "ans": "len_MN - len_MP",
        "w1": "len_MN + len_MP",
        "w2": "len_MP",
        "w3": "len_MN"
      },
      "questionText": "Trên một sợi dây cáp quang dài {len_MN} mét, có các điểm kiểm tra M, N và P. Biết rằng điểm P nằm giữa điểm M và điểm N. Khoảng cách từ M đến P là {len_MP} mét. Hỏi khoảng cách từ P đến N là bao nhiêu mét?",
      "options": [
        "A. {w1} mét",
        "B. {ans} mét",
        "C. {w2} mét",
        "D. {w3} mét"
      ],
      "correctIndex": 1,
      "hints": [
        "Nếu P nằm giữa M và N, thì $MP + PN = MN$.",
        "Từ đó, ta có thể tìm PN bằng cách lấy $MN - MP$."
      ],
      "solutionHtml": "Vì điểm P nằm giữa điểm M và điểm N, theo định nghĩa ta có:<br/>$MN = MP + PN$<br/>Để tìm khoảng cách từ P đến N ($PN$), ta thực hiện phép trừ:<br/>$PN = MN - MP$<br/>Thay số vào, ta được:<br/>$PN = {len_MN} - {len_MP} = {ans}$ mét.<br/>Vậy khoảng cách từ P đến N là {ans} mét.<br/>Đáp án đúng là B.",
      "tip": "Bài toán này là dạng ngược của bài toán tìm tổng độ dài khi biết điểm nằm giữa. Nắm vững công thức $MP + PN = MN$ là chìa khóa."
    },
    {
      "isTemplate": true,
      "variables": {
        "num_cameras": {
          "min": 4,
          "max": 10,
          "step": 1
        }
      },
      "constraints": [
        "num_cameras >= 2"
      ],
      "formulas": {
        "ans": "num_cameras * 2",
        "w1": "num_cameras",
        "w2": "num_cameras * (num_cameras - 1) / 2",
        "w3": "num_cameras + (num_cameras - 1)"
      },
      "questionText": "Trên một hàng rào thẳng, người ta lắp đặt {num_cameras} camera an ninh phân biệt. Mỗi camera có khả năng quay và chiếu sáng theo hai hướng ngược chiều nhau trên hàng rào (tạo thành hai tia đối nhau có gốc là vị trí camera). Hỏi có tất cả bao nhiêu tia chiếu sáng phân biệt được tạo ra trên hàng rào đó?",
      "options": [
        "A. {w1} tia",
        "B. {ans} tia",
        "C. {w2} tia",
        "D. {w3} tia"
      ],
      "correctIndex": 1,
      "hints": [
        "Mỗi điểm trên đường thẳng là gốc của hai tia đối nhau.",
        "Với {num_cameras} điểm phân biệt trên đường thẳng, mỗi điểm tạo ra 2 tia độc lập."
      ],
      "solutionHtml": "Theo định nghĩa, mỗi điểm trên một đường thẳng là gốc của hai tia đối nhau. Nếu có {num_cameras} camera (tức {num_cameras} điểm phân biệt) trên hàng rào thẳng, mỗi camera sẽ tạo ra 2 tia chiếu sáng phân biệt (một tia đi về bên trái và một tia đi về bên phải).<br/>Tổng số tia chiếu sáng phân biệt được tạo ra là:<br/>$ {num_cameras} \\times 2 = {ans} $ (tia).<br/>Vậy có tất cả {ans} tia chiếu sáng phân biệt.<br/>Đáp án đúng là B.",
      "tip": "Đếm số tia trên đường thẳng có $n$ điểm: mỗi điểm là gốc của 2 tia (một về bên này, một về bên kia). Do đó tổng số tia là $2n$."
    },
    {
      "isTemplate": true,
      "variables": {
        "len_AB": {
          "min": 8,
          "max": 20,
          "step": 2
        },
        "len_BC": {
          "min": 5,
          "max": 15,
          "step": 1
        },
        "len_CD": {
          "min": 7,
          "max": 18,
          "step": 1
        }
      },
      "constraints": [],
      "formulas": {
        "ans": "len_AB + len_BC + len_CD",
        "w1": "len_AB + len_BC",
        "w2": "len_BC + len_CD",
        "w3": "len_AB + len_CD"
      },
      "questionText": "Bốn cột mốc A, B, C, D được dựng thẳng hàng theo thứ tự đó trên một con đường. Khoảng cách giữa A và B là {len_AB} mét, giữa B và C là {len_BC} mét, và giữa C và D là {len_CD} mét. Hỏi tổng chiều dài đoạn đường từ A đến D là bao nhiêu mét?",
      "options": [
        "A. {w1} mét",
        "B. {ans} mét",
        "C. {w2} mét",
        "D. {w3} mét"
      ],
      "correctIndex": 1,
      "hints": [
        "Vì các điểm A, B, C, D nằm thẳng hàng theo thứ tự, B nằm giữa A và C, C nằm giữa B và D.",
        "Đoạn AD sẽ bằng tổng của các đoạn AB, BC, CD."
      ],
      "solutionHtml": "Vì các cột mốc A, B, C, D được dựng thẳng hàng theo thứ tự đó, điều này có nghĩa là B nằm giữa A và C, và C nằm giữa B và D (đồng thời B và C cũng nằm giữa A và D).<br/>Do đó, độ dài đoạn thẳng AD sẽ bằng tổng độ dài của các đoạn thẳng con:<br/>$AD = AB + BC + CD$<br/>Thay số vào, ta có:<br/>$AD = {len_AB} + {len_BC} + {len_CD} = {ans}$ mét.<br/>Vậy tổng chiều dài đoạn đường từ A đến D là {ans} mét.<br/>Đáp án đúng là B.",
      "tip": "Khi nhiều điểm nằm thẳng hàng theo thứ tự, độ dài đoạn thẳng lớn nhất sẽ bằng tổng độ dài của các đoạn thẳng con tạo nên nó."
    },
    {
      "isTemplate": true,
      "variables": {
        "total_length": {
          "min": 60,
          "max": 120,
          "step": 10
        },
        "spacing": {
          "min": 5,
          "max": 15,
          "step": 5
        }
      },
      "constraints": [
        "total_length % spacing === 0"
      ],
      "formulas": {
        "total_sections": "total_length / spacing",
        "ans": "total_sections - 1",
        "w1": "total_sections",
        "w2": "total_sections + 1",
        "w3": "total_sections - 2"
      },
      "questionText": "Một đoạn đường thẳng dài {total_length} mét được trang trí bằng dây đèn LED. Các bóng đèn được đặt cách đều nhau {spacing} mét, bắt đầu từ điểm đầu đường và kết thúc tại điểm cuối đường. Hỏi có bao nhiêu bóng đèn NẰM GIỮA điểm đầu và điểm cuối của đoạn đường đó?",
      "options": [
        "A. {w1} bóng đèn",
        "B. {ans} bóng đèn",
        "C. {w2} bóng đèn",
        "D. {w3} bóng đèn"
      ],
      "correctIndex": 1,
      "hints": [
        "Tổng số khoảng cách giữa các bóng đèn là $\\frac{\\text{tổng chiều dài}}{\\text{khoảng cách giữa hai bóng đèn}}$ (số khoảng trống).",
        "Nếu có $k$ khoảng cách, thì có $k+1$ bóng đèn. Số bóng đèn nằm giữa hai đầu là $(k+1) - 2$."
      ],
      "solutionHtml": "Tổng chiều dài đoạn đường là {total_length} mét.<br/>Khoảng cách giữa hai bóng đèn liên tiếp là {spacing} mét.<br/>Số khoảng cách giữa các bóng đèn trên đoạn đường là: $ {total_length} \\div {spacing} = {total_sections} $.<br/>Nếu có $k$ khoảng cách, thì sẽ có $k+1$ bóng đèn (tính cả bóng đèn ở hai đầu).<br/>Số bóng đèn tổng cộng là $ {total_sections} + 1 = {total_sections + 1} $ bóng đèn.<br/>Vì đề bài hỏi số bóng đèn NẰM GIỮA điểm đầu và điểm cuối (tức là không tính hai bóng đèn ở hai đầu), ta lấy tổng số bóng đèn trừ đi 2.<br/>Số bóng đèn nằm giữa là $ ({total_sections} + 1) - 2 = {total_sections - 1} = {ans} $ bóng đèn.<br/>Đáp án đúng là B.",
      "tip": "Bài toán đếm vật thể trên đoạn thẳng. Nếu có $k$ khoảng trống, thì có $k+1$ vật thể. Nếu muốn đếm vật thể nằm giữa hai đầu, trừ đi 2."
    },
    {
      "isTemplate": true,
      "variables": {
        "num_stations": {
          "min": 4,
          "max": 8,
          "step": 1
        }
      },
      "constraints": [
        "num_stations >= 3"
      ],
      "formulas": {
        "num_segments": "num_stations * (num_stations - 1) / 2",
        "num_rays": "num_stations * 2",
        "ans": "num_segments + num_rays",
        "w1": "num_segments",
        "w2": "num_rays",
        "w3": "num_segments + num_rays + 1"
      },
      "questionText": "Trên một đường thẳng có {num_stations} trạm dừng xe buýt phân biệt. Người ta muốn tính tổng số 'đoạn đường nội bộ' (nối giữa hai trạm bất kỳ) và số 'tuyến vận chuyển' (là các tia xuất phát từ mỗi trạm theo hai hướng) có thể tạo thành. Hỏi tổng số 'đoạn đường nội bộ' và 'tuyến vận chuyển' là bao nhiêu?",
      "options": [
        "A. {w1}",
        "B. {ans}",
        "C. {w2}",
        "D. {w3}"
      ],
      "correctIndex": 1,
      "hints": [
        "Đầu tiên, hãy tính số đoạn thẳng được tạo thành từ {num_stations} điểm phân biệt.",
        "Tiếp theo, tính số tia được tạo thành từ {num_stations} điểm phân biệt trên đường thẳng.",
        "Cuối cùng, cộng hai kết quả lại."
      ],
      "solutionHtml": "Gọi số trạm dừng xe buýt là $n = {num_stations}$.<br/>1. Số 'đoạn đường nội bộ' (số đoạn thẳng):<br/>    Từ $n$ điểm phân biệt trên một đường thẳng, số đoạn thẳng tạo thành là $ \\frac{n(n-1)}{2} $.<br/>    Vậy, số đoạn đường nội bộ là $ \\frac{{num_stations} \\times ({num_stations} - 1)}{2} = {num_segments} $.<br/>2. Số 'tuyến vận chuyển' (số tia):<br/>    Mỗi điểm trên đường thẳng là gốc của hai tia đối nhau. Với $n$ điểm phân biệt, số tia tạo thành là $2n$.<br/>    Vậy, số tuyến vận chuyển là $ {num_stations} \\times 2 = {num_rays} $.<br/>Tổng số 'đoạn đường nội bộ' và 'tuyến vận chuyển' là:<br/>    $ {num_segments} + {num_rays} = {ans} $.<br/>Đáp án đúng là B.",
      "tip": "Phân tích bài toán thành hai phần riêng biệt: đếm đoạn thẳng và đếm tia, sau đó cộng các kết quả lại."
    },
    {
      "isTemplate": true,
      "variables": {
        "len_OA": {
          "min": 5,
          "max": 15,
          "step": 1
        },
        "len_OB": {
          "min": 16,
          "max": 30,
          "step": 1
        }
      },
      "constraints": [
        "len_OB > len_OA"
      ],
      "formulas": {
        "len_AB": "len_OB - len_OA",
        "w1_len_AB_wrong": "len_OB + len_OA",
        "ans_statement": "'Điểm A nằm giữa hai điểm O và B, và độ dài đoạn AB là ${len_AB}$ cm.'",
        "w1_statement": "'Điểm B nằm giữa hai điểm O và A, và độ dài đoạn AB là ${len_OB - len_OA}$ cm.'",
        "w2_statement": "'Điểm A nằm giữa hai điểm O và B, và độ dài đoạn AB là ${w1_len_AB_wrong}$ cm.'",
        "w3_statement": "'Không có điểm nào nằm giữa hai điểm còn lại.'"
      },
      "questionText": "Trên tia $Ox$, người ta lấy hai điểm A và B. Biết rằng $OA = {len_OA}$ cm và $OB = {len_OB}$ cm. Khẳng định nào sau đây là đúng?",
      "options": [
        "A. {w1_statement}",
        "B. {ans_statement}",
        "C. {w2_statement}",
        "D. {w3_statement}"
      ],
      "correctIndex": 1,
      "hints": [
        "Trên tia $Ox$, nếu $OA < OB$ thì điểm A nằm giữa O và B.",
        "Nếu A nằm giữa O và B, thì $OA + AB = OB$."
      ],
      "solutionHtml": "Vì điểm A và điểm B cùng nằm trên tia $Ox$, và $OA = {len_OA}$ cm, $OB = {len_OB}$ cm.<br/>Ta thấy $OA = {len_OA} < OB = {len_OB}$.<br/>Theo tính chất của điểm trên tia, nếu $OA < OB$ thì điểm A nằm giữa điểm O và điểm B.<br/>Khi đó, ta có hệ thức:<br/>$OA + AB = OB$<br/>Để tìm độ dài đoạn AB, ta lấy $AB = OB - OA = {len_OB} - {len_OA} = {len_AB}$ cm.<br/>Vậy, khẳng định đúng là: {ans_statement}<br/>Đáp án đúng là B.",
      "tip": "Khi các điểm nằm trên cùng một tia xuất phát từ một gốc O, điểm nào có khoảng cách đến O nhỏ hơn thì điểm đó nằm gần O hơn và nằm giữa điểm O và điểm có khoảng cách lớn hơn."
    },
    {
      "isTemplate": true,
      "variables": {
        "num_people": {
          "min": 5,
          "max": 10,
          "step": 1
        },
        "total_length": {
          "min": 50,
          "max": 100,
          "step": 10
        },
        "person_A_index": {
          "min": 1,
          "max": 4,
          "step": 1
        },
        "person_B_index": {
          "min": 5,
          "max": 9,
          "step": 1
        }
      },
      "constraints": [
        "num_people >= 2",
        "total_length % (num_people - 1) === 0",
        "person_A_index < person_B_index",
        "person_A_index >= 1",
        "person_B_index <= num_people"
      ],
      "formulas": {
        "spacing": "total_length / (num_people - 1)",
        "ans": "(person_B_index - person_A_index) * spacing",
        "w1": "(person_B_index + person_A_index) * spacing",
        "w2": "total_length / num_people",
        "w3": "(person_B_index - person_A_index) * total_length"
      },
      "questionText": "Trong một buổi tập duyệt đội hình, có {num_people} người đứng thẳng hàng, cách đều nhau. Người thứ nhất đứng ở vị trí 0 mét. Người thứ {num_people} đứng ở vị trí {total_length} mét. Hỏi khoảng cách giữa người thứ {person_A_index} và người thứ {person_B_index} là bao nhiêu mét?",
      "options": [
        "A. {w1} mét",
        "B. {ans} mét",
        "C. {w2} mét",
        "D. {w3} mét"
      ],
      "correctIndex": 1,
      "hints": [
        "Đầu tiên, hãy tính khoảng cách đều giữa hai người liên tiếp.",
        "Số khoảng trống giữa {num_people} người là {num_people} - 1$.",
        "Khoảng cách giữa người thứ {person_A_index} và người thứ {person_B_index} là $ ( {person_B_index} - {person_A_index} ) \\times \\text{khoảng cách giữa hai người liên tiếp}$."
      ],
      "solutionHtml": "Có {num_people} người đứng thẳng hàng, cách đều nhau.<br/>Người thứ nhất ở vị trí 0 mét, người thứ {num_people} ở vị trí {total_length} mét.<br/>Số khoảng cách giữa {num_people} người là $ {num_people} - 1 $.<br/>Khoảng cách đều giữa hai người liên tiếp là: $ \\frac{{total_length}}{{{num_people} - 1}} = {spacing} $ mét.<br/>Để tìm khoảng cách giữa người thứ {person_A_index} và người thứ {person_B_index}, ta nhân số khoảng cách giữa họ với khoảng cách đều:<br/>Số khoảng cách giữa người thứ {person_A_index} và người thứ {person_B_index} là $ {person_B_index} - {person_A_index} $.<br/>Khoảng cách cần tìm là $ ({person_B_index} - {person_A_index}) \\times {spacing} = {ans} $ mét.<br/>Đáp án đúng là B.",
      "tip": "Xác định rõ ràng tổng số khoảng trống, từ đó tìm được giá trị của mỗi khoảng trống. Sau đó, nhân với số khoảng trống giữa hai đối tượng cụ thể."
    },
    {
      "isTemplate": true,
      "variables": {
        "num_points": {
          "min": 4,
          "max": 10,
          "step": 1
        }
      },
      "constraints": [
        "num_points >= 3"
      ],
      "formulas": {
        "ans": "num_points * (num_points - 1) * (num_points - 2) / 6",
        "w1": "num_points * (num_points - 1) / 2",
        "w2": "num_points * 2",
        "w3": "num_points * (num_points - 1) * (num_points - 2)"
      },
      "questionText": "Một nhà khảo sát đánh dấu {num_points} điểm phân biệt trên một con đường thẳng để nghiên cứu. Hỏi có bao nhiêu cách chọn 3 điểm khác nhau từ các điểm đã đánh dấu sao cho luôn có một điểm nằm giữa hai điểm còn lại?",
      "options": [
        "A. {w1} cách",
        "B. {ans} cách",
        "C. {w2} cách",
        "D. {w3} cách"
      ],
      "correctIndex": 1,
      "hints": [
        "Khi ba điểm nằm trên một đường thẳng, luôn có một điểm nằm giữa hai điểm còn lại.",
        "Vậy bài toán này tương đương với việc đếm số cách chọn 3 điểm bất kỳ từ {num_points} điểm phân biệt."
      ],
      "solutionHtml": "Khi ba điểm phân biệt nằm trên một đường thẳng, chắc chắn sẽ có một điểm nằm giữa hai điểm còn lại. Do đó, bài toán này quy về việc đếm số cách chọn 3 điểm bất kỳ từ {num_points} điểm đã cho.<br/>Số cách chọn 3 điểm từ $n$ điểm phân biệt (mà không quan tâm đến thứ tự) được tính bằng công thức tổ hợp $C_n^3$:<br/>$ C_n^3 = \\frac{n(n-1)(n-2)}{3 \\times 2 \\times 1} $<br/>Thay $n = {num_points}$ vào, ta có:<br/>$ \\frac{{num_points} \\times ({num_points} - 1) \\times ({num_points} - 2)}{6} = {ans} $ (cách).<br/>Vậy có tất cả {ans} cách chọn 3 điểm thỏa mãn yêu cầu.<br/>Đáp án đúng là B.",
      "tip": "Khi các điểm đã cho là các điểm phân biệt trên cùng một đường thẳng, bất kỳ ba điểm nào được chọn cũng sẽ thỏa mãn điều kiện 'có một điểm nằm giữa hai điểm còn lại'. Vì vậy, đây là một bài toán tổ hợp đơn giản $C_n^3$."
    }
  ]
}