{
  "questions": [
    {
      "isTemplate": true,
      "variables": {
        "ngay1": {
          "min": 250,
          "max": 400,
          "step": 10
        },
        "factorNgay2": {
          "min": 2,
          "max": 4,
          "step": 1
        },
        "lessNgay3": {
          "min": 50,
          "max": 150,
          "step": 10
        }
      },
      "constraints": [
        "variables.ngay1 * variables.factorNgay2 > variables.lessNgay3 + 100"
      ],
      "formulas": {
        "ngay2": "variables.ngay1 * variables.factorNgay2",
        "ngay3": "variables.ngay1 * variables.factorNgay2 - variables.lessNgay3",
        "ans": "variables.ngay1 + (variables.ngay1 * variables.factorNgay2) + (variables.ngay1 * variables.factorNgay2 - variables.lessNgay3)",
        "w1_goc": "variables.ngay1 + (variables.ngay1 * variables.factorNgay2)",
        "w2_goc": "variables.ngay1 + (variables.ngay1 * variables.factorNgay2 - variables.lessNgay3)",
        "w3_goc": "(variables.ngay1 * variables.factorNgay2) + (variables.ngay1 * variables.factorNgay2 - variables.lessNgay3)",
        "w1": "(w1_goc === ans) ? w1_goc + 10 : w1_goc",
        "w2": "(w2_goc === ans || w2_goc === w1) ? (w1 + 20) : w2_goc",
        "w3": "(w3_goc === ans || w3_goc === w1 || w3_goc === w2) ? (ans + 30) : w3_goc"
      },
      "questionText": "Một vườn cam thu hoạch trong ba ngày. Ngày thứ nhất thu hoạch được {ngay1} kg. Ngày thứ hai thu hoạch được số cam gấp {factorNgay2} lần ngày thứ nhất. Ngày thứ ba thu hoạch được số cam ít hơn ngày thứ hai {lessNgay3} kg. Hỏi cả ba ngày vườn cam đó thu hoạch được tất cả bao nhiêu ki-lô-gam cam?",
      "options": [
        "A. {w1} kg",
        "B. {ans} kg",
        "C. {w2} kg",
        "D. {w3} kg"
      ],
      "correctIndex": 1,
      "hints": [
        "Đầu tiên, hãy tính số cam thu hoạch được trong ngày thứ hai bằng phép nhân.",
        "Tiếp theo, hãy tính số cam thu hoạch được trong ngày thứ ba bằng phép trừ.",
        "Cuối cùng, tính tổng số cam thu hoạch được trong cả ba ngày."
      ],
      "solutionHtml": "Số cam thu hoạch được trong ngày thứ hai là:<br/>{ngay1} $ \\times $ {factorNgay2} = {ngay2} (kg)<br/><br/>Số cam thu hoạch được trong ngày thứ ba là:<br/>{ngay2} $ - $ {lessNgay3} = {ngay3} (kg)<br/><br/>Tổng số cam thu hoạch được trong cả ba ngày là:<br/>{ngay1} $ + $ {ngay2} $ + $ {ngay3} = {ans} (kg)<br/><br/>Đáp án đúng là B.",
      "tip": "Đọc kỹ đề bài để xác định đúng thứ tự các phép tính và tránh nhầm lẫn giữa 'gấp mấy lần' và 'ít hơn' hoặc 'nhiều hơn'.",
      "level": "chat-luong-cao",
      "type": "l4-kt-c3-d1"
    },
    {
      "isTemplate": true,
      "variables": {
        "tongBanh": {
          "min": 1250,
          "max": 1800,
          "step": 50
        },
        "banhMoiHop": {
          "min": 12,
          "max": 20,
          "step": 1
        }
      },
      "constraints": [
        "tongBanh > banhMoiHop",
        "banhMoiHop > 1"
      ],
      "formulas": {
        "soHopDu": "Math.floor(tongBanh / banhMoiHop)",
        "soBanhThua": "tongBanh % banhMoiHop",
        "tongSoHopCan": "soBanhThua === 0 ? soHopDu : soHopDu + 1",
        "ans": "soBanhThua === 0 ? `Cần ${soHopDu} hộp, không thừa bánh nào.` : `Cần ${soHopDu + 1} hộp, còn thừa ${soBanhThua} cái bánh.`",
        "w1_raw": "soBanhThua === 0 ? `Cần ${soHopDu + 1} hộp, không thừa bánh nào.` : `Cần ${soHopDu} hộp, còn thừa ${soBanhThua} cái bánh.`",
        "w2_raw": "soBanhThua === 0 ? `Cần ${soHopDu + 2} hộp, không thừa bánh nào.` : `Cần ${soHopDu + 1} hộp, không thừa bánh nào.`",
        "w3_raw": "soBanhThua === 0 ? `Cần ${soHopDu} hộp, còn thừa 1 cái bánh.` : `Cần ${soHopDu + 2} hộp, còn thừa ${soBanhThua} cái bánh.`",
        "w1": "(w1_raw === ans) ? `Cần ${soHopDu + 3} hộp, còn thừa ${soBanhThua + 1} cái bánh.` : w1_raw",
        "w2": "(w2_raw === ans || w2_raw === w1) ? `Cần ${soHopDu + 4} hộp, còn thừa ${soBanhThua + 2} cái bánh.` : w2_raw",
        "w3": "(w3_raw === ans || w3_raw === w1 || w3_raw === w2) ? `Cần ${soHopDu + 5} hộp, còn thừa ${soBanhThua + 3} cái bánh.` : w3_raw"
      },
      "questionText": "Bác An có {tongBanh} cái bánh ngọt. Bác muốn xếp số bánh này vào các hộp, mỗi hộp đựng được {banhMoiHop} cái bánh. Hỏi bác An cần ít nhất bao nhiêu hộp để xếp hết số bánh đó và còn thừa bao nhiêu cái bánh?",
      "options": [
        "A. {w1}",
        "B. {ans}",
        "C. {w2}",
        "D. {w3}"
      ],
      "correctIndex": 1,
      "hints": [
        "Hãy thực hiện phép chia {tongBanh} chia {banhMoiHop} để tìm số hộp đầy và số bánh còn lại.",
        "Nếu có bánh còn lại sau khi xếp đầy các hộp, bác An sẽ cần thêm một hộp nữa để đựng số bánh đó."
      ],
      "solutionHtml": "Thực hiện phép chia số bánh ngọt cho số bánh mỗi hộp:<br/>{tongBanh} : {banhMoiHop} = {soHopDu} (dư {soBanhThua})<br/><br/>Số hộp đầy là {soHopDu} hộp.<br/>Số bánh còn thừa là {soBanhThua} cái.<br/><br/>Nếu số bánh còn thừa lớn hơn 0, ta cần thêm 1 hộp nữa để đựng số bánh thừa đó.<br/>Vậy tổng số hộp cần ít nhất là {tongSoHopCan} hộp.<br/><br/>Đáp án đúng là: {ans}",
      "tip": "Khi bài toán yêu cầu 'cần ít nhất bao nhiêu hộp để xếp hết', bạn phải tính cả hộp chứa số dư (nếu có dư).",
      "level": "chat-luong-cao",
      "type": "l4-kt-c3-d2"
    },
    {
      "isTemplate": true,
      "variables": {
        "diemToan": {
          "min": 7,
          "max": 10,
          "step": 1
        },
        "diemTV": {
          "min": 7,
          "max": 10,
          "step": 1
        },
        "chenhLech": {
          "min": 1,
          "max": 3,
          "step": 1
        }
      },
      "constraints": [
        "(diemToan + diemTV - 3 * chenhLech) > 0",
        "(diemToan + diemTV - 3 * chenhLech) % 2 === 0"
      ],
      "formulas": {
        "tongHaiMon": "diemToan + diemTV",
        "baLanChenhLech": "3 * chenhLech",
        "tuSo": "diemToan + diemTV - 3 * chenhLech",
        "ans": "(diemToan + diemTV - 3 * chenhLech) / 2",
        "w1_goc": "ans + 1",
        "w2_goc": "ans + 2",
        "w3_goc": "ans + 3",
        "w1": "w1_goc",
        "w2": "w2_goc",
        "w3": "w3_goc"
      },
      "questionText": "An kiểm tra ba môn học. Môn Toán được {diemToan} điểm, môn Tiếng Việt được {diemTV} điểm. Điểm môn Khoa học kém trung bình cộng điểm ba môn là {chenhLech} điểm. Hỏi điểm môn Khoa học của An là bao nhiêu?",
      "options": [
        "A. {w1} điểm",
        "B. {ans} điểm",
        "C. {w2} điểm",
        "D. {w3} điểm"
      ],
      "correctIndex": 1,
      "hints": [
        "Gọi điểm môn Khoa học là X. Trung bình cộng ba môn bằng tổng điểm ba môn chia cho 3.",
        "Điểm Khoa học bằng trung bình cộng trừ đi {chenhLech}.",
        "Nhân trung bình cộng với 3 để tìm tổng ba môn, từ đó giải bài toán tìm số chưa biết X."
      ],
      "solutionHtml": "Gọi điểm môn Khoa học là X. Trung bình cộng điểm ba môn là tổng của {diemToan}, {diemTV} và X, sau đó chia cho 3. Theo đề bài, ta có X bằng trung bình cộng trừ đi {chenhLech}. Nhân cả hai vế với 3, ta được: 3 nhân X bằng {diemToan} cộng {diemTV} cộng X trừ {baLanChenhLech}. Chuyển X sang vế trái: 2 nhân X bằng {tongHaiMon} trừ {baLanChenhLech}. Vậy 2 nhân X bằng {tuSo}, suy ra X bằng {tuSo} chia 2 bằng {ans}. Vậy điểm môn Khoa học của An là {ans} điểm.",
      "tip": "Khi gặp bài toán trung bình cộng có chứa một ẩn số, hãy nhân trung bình cộng với số lượng các số hạng để quy về bài toán tìm tổng, giúp việc tính toán trở nên đơn giản hơn.",
      "level": "chat-luong-cao",
      "type": "l4-kt-c3-d3"
    },
    {
      "isTemplate": true,
      "variables": {
        "factor": {
          "min": 6,
          "max": 9,
          "step": 1
        },
        "tru": {
          "min": 150,
          "max": 300,
          "step": 10
        },
        "chia": {
          "min": 2,
          "max": 5,
          "step": 1
        },
        "ketQua": {
          "min": 100,
          "max": 250,
          "step": 10
        }
      },
      "constraints": [
        "variables.ketQua * variables.chia > variables.tru + 50",
        "(variables.ketQua * variables.chia + variables.tru) % variables.factor === 0",
        "variables.ketQua % variables.chia === 0"
      ],
      "formulas": {
        "buoc1": "variables.ketQua * variables.chia",
        "buoc2": "variables.ketQua * variables.chia + variables.tru",
        "ans": "(variables.ketQua * variables.chia + variables.tru) / variables.factor",
        "w1_goc": "variables.ans + 10",
        "w2_goc": "variables.ans - 10",
        "w3_goc": "variables.ans * 2",
        "w1": "variables.w1_goc",
        "w2": "(variables.w2_goc === variables.ans || variables.w2_goc <= 0) ? variables.ans + 20 : variables.w2_goc",
        "w3": "(variables.w3_goc === variables.ans || variables.w3_goc === variables.w1 || variables.w3_goc === variables.w2) ? variables.ans + 30 : variables.w3_goc"
      },
      "questionText": "Một số, sau khi nhân với {factor}, rồi trừ đi {tru}, rồi chia cho {chia} thì được kết quả là {ketQua}. Tìm số ban đầu.",
      "options": [
        "A. {w1}",
        "B. {ans}",
        "C. {w2}",
        "D. {w3}"
      ],
      "correctIndex": 1,
      "hints": [
        "Để tìm số ban đầu, ta phải thực hiện các phép tính ngược lại và theo thứ tự ngược lại.",
        "Bước cuối cùng là chia cho {chia} ra {ketQua}. Vậy trước đó là phép tính nhân để ra số bị chia.",
        "Bước trước nữa là trừ đi {tru}. Vậy trước đó là phép tính cộng để ra số bị trừ.",
        "Bước đầu tiên là nhân với {factor}. Vậy làm thế nào để tìm số ban đầu?"
      ],
      "solutionHtml": "Để tìm số ban đầu, ta thực hiện các phép tính ngược lại:<br/>1. Kết quả cuối cùng là {ketQua} sau khi chia cho {chia}. Số trước khi chia là: {ketQua} $\\times$ {chia} = {buoc1}<br/>2. Số {buoc1} có được sau khi trừ đi {tru}. Số trước khi trừ là: {buoc1} + {tru} = {buoc2}<br/>3. Số {buoc2} có được sau khi nhân với {factor}. Số ban đầu là: {buoc2} : {factor} = {ans}<br/>Vậy số ban đầu là {ans}.",
      "tip": "Khi giải bài toán tìm số ban đầu với các phép tính liên tiếp, hãy làm ngược lại từ kết quả cuối cùng, đảo ngược mỗi phép tính: Cộng thành trừ, trừ thành cộng, nhân thành chia, chia thành nhân.",
      "level": "chat-luong-cao",
      "type": "l4-kt-c3-d4"
    },
    {
      "isTemplate": true,
      "variables": {
        "soLuongSP": {
          "min": 500,
          "max": 800,
          "step": 50
        },
        "giaNhap": {
          "min": 20000,
          "max": 35000,
          "step": 1000
        },
        "soLuongBanCao": {
          "min": 300,
          "max": 450,
          "step": 20
        },
        "giaBanCao": {
          "min": 40000,
          "max": 60000,
          "step": 2000
        },
        "giaBanThap": {
          "min": 25000,
          "max": 38000,
          "step": 1000
        }
      },
      "constraints": [
        "soLuongSP > soLuongBanCao",
        "giaBanCao > (giaNhap + 5000)",
        "giaBanThap > (giaNhap - 5000)",
        "giaBanThap < giaBanCao",
        "((soLuongBanCao * giaBanCao) + ((soLuongSP - soLuongBanCao) * giaBanThap)) > (soLuongSP * giaNhap)"
      ],
      "formulas": {
        "tienNhap": "soLuongSP * giaNhap",
        "soLuongConLai": "soLuongSP - soLuongBanCao",
        "tienBanCao": "soLuongBanCao * giaBanCao",
        "tienBanThap": "(soLuongSP - soLuongBanCao) * giaBanThap",
        "tongTienBan": "(soLuongBanCao * giaBanCao) + ((soLuongSP - soLuongBanCao) * giaBanThap)",
        "ans": "((soLuongBanCao * giaBanCao) + ((soLuongSP - soLuongBanCao) * giaBanThap)) - (soLuongSP * giaNhap)",
        "w1_raw": "ans + 10000",
        "w2_raw": "ans - 5000",
        "w3_raw": "ans + 20000",
        "w1": "(w1_raw === ans) ? ans + 15000 : w1_raw",
        "w2": "(w2_raw === ans || w2_raw === w1) ? ans + 25000 : w2_raw",
        "w3": "(w3_raw === ans || w3_raw === w1 || w3_raw === w2) ? ans + 35000 : w3_raw"
      },
      "questionText": "Một cửa hàng nhập về {soLuongSP} chiếc áo với giá {giaNhap} đồng/chiếc. Họ bán được {soLuongBanCao} chiếc áo với giá {giaBanCao} đồng/chiếc. Số áo còn lại được bán với giá {giaBanThap} đồng/chiếc. Hỏi sau khi bán hết số áo, cửa hàng đó lãi bao nhiêu tiền?",
      "options": [
        "A. {w1} đồng",
        "B. {ans} đồng",
        "C. {w2} đồng",
        "D. {w3} đồng"
      ],
      "correctIndex": 1,
      "hints": [
        "Đầu tiên, hãy tính tổng số tiền vốn đã bỏ ra để nhập áo.",
        "Sau đó, tính số lượng áo còn lại sau khi bán đợt đầu.",
        "Tính tổng số tiền thu được từ việc bán áo, chia thành hai đợt giá khác nhau.",
        "Cuối cùng, tính số tiền lãi bằng cách lấy tổng tiền bán trừ đi tổng tiền vốn."
      ],
      "solutionHtml": "Tổng số tiền vốn cửa hàng đã bỏ ra là:<br/>{soLuongSP} $\\times$ {giaNhap} = {tienNhap} (đồng)<br/><br/>Số áo còn lại sau khi bán đợt đầu là:<br/>{soLuongSP} $-$ {soLuongBanCao} = {soLuongConLai} (chiếc)<br/><br/>Số tiền thu được từ việc bán {soLuongBanCao} chiếc áo đầu tiên là:<br/>{soLuongBanCao} $\\times$ {giaBanCao} = {tienBanCao} (đồng)<br/><br/>Số tiền thu được từ việc bán {soLuongConLai} chiếc áo còn lại là:<br/>{soLuongConLai} $\\times$ {giaBanThap} = {tienBanThap} (đồng)<br/><br/>Tổng số tiền cửa hàng thu được khi bán hết áo là:<br/>{tienBanCao} $+$ {tienBanThap} = {tongTienBan} (đồng)<br/><br/>Số tiền lãi của cửa hàng là:<br/>{tongTienBan} $-$ {tienNhap} = {ans} (đồng)<br/><br/>Đáp án đúng là B.",
      "tip": "Khi bài toán có nhiều bước tính toán và các mức giá khác nhau, hãy chia nhỏ bài toán thành từng phần rõ ràng: tính vốn, tính tiền thu được từ mỗi loại hàng bán, rồi tính tổng doanh thu và so sánh với tổng vốn.",
      "level": "chat-luong-cao",
      "type": "l4-kt-c3-d5"
    },
    {
      "isTemplate": true,
      "variables": {
        "tong": {
          "min": 800,
          "max": 1500,
          "step": 50
        },
        "lan": {
          "min": 3,
          "max": 6,
          "step": 1
        }
      },
      "constraints": [
        "tong % (lan + 1) === 0",
        "tong % lan === 0"
      ],
      "formulas": {
        "tongSoPhan": "lan + 1",
        "ans": "tong / (lan + 1)",
        "soLon": "tong - (tong / (lan + 1))",
        "w1_goc": "tong / lan",
        "w2_goc": "tong - (tong / (lan + 1))",
        "w3_goc": "tong * lan",
        "w1": "(w1_goc === ans) ? ans + 100 : w1_goc",
        "w2": "(w2_goc === ans || w2_goc === w1) ? ans + 200 : w2_goc",
        "w3": "(w3_goc === ans || w3_goc === w1 || w3_goc === w2) ? ans + 300 : w3_goc"
      },
      "questionText": "Hai số có tổng là {tong}. Biết số lớn gấp {lan} lần số bé. Tìm số bé.",
      "options": [
        "A. {w1}",
        "B. {ans}",
        "C. {w2}",
        "D. {w3}"
      ],
      "correctIndex": 1,
      "hints": [
        "Hãy vẽ sơ đồ đoạn thẳng biểu thị số lớn và số bé.",
        "Xác định tổng số phần bằng nhau.",
        "Tìm giá trị của một phần, đó chính là số bé."
      ],
      "solutionHtml": "Vì số lớn gấp {lan} lần số bé, ta có thể biểu diễn số bé là 1 phần, số lớn là {lan} phần.<br/>Tổng số phần bằng nhau là: 1 + {lan} = {tongSoPhan} (phần)<br/><br/>Giá trị của một phần (chính là số bé) là: {tong} : {tongSoPhan} = {ans}<br/><br/>Vậy số bé là {ans}.<br/>(Số lớn là {ans} x {lan} = {soLon})<br/>Đáp án đúng là B.",
      "tip": "Đối với dạng toán tìm hai số khi biết tổng và tỉ số, hãy tìm tổng số phần bằng nhau, sau đó lấy tổng của hai số chia cho tổng số phần để tìm giá trị của một phần.",
      "level": "chat-luong-cao",
      "type": "l4-kt-c3-d6"
    },
    {
      "isTemplate": true,
      "variables": {
        "tongTuoiHienTai": {
          "min": 70,
          "max": 90,
          "step": 2
        },
        "chenhLechTuoi": {
          "min": 50,
          "max": 65,
          "step": 2
        },
        "lan": {
          "min": 3,
          "max": 5,
          "step": 1
        }
      },
      "constraints": [
        "tongTuoiHienTai > chenhLechTuoi",
        "(tongTuoiHienTai - chenhLechTuoi) % 2 === 0",
        "lan > 1",
        "(((tongTuoiHienTai - chenhLechTuoi) / 2) + chenhLechTuoi - lan * ((tongTuoiHienTai - chenhLechTuoi) / 2)) > 0",
        "(((tongTuoiHienTai - chenhLechTuoi) / 2) + chenhLechTuoi - lan * ((tongTuoiHienTai - chenhLechTuoi) / 2)) % (lan - 1) === 0"
      ],
      "formulas": {
        "tuoiChauHienTai": "(tongTuoiHienTai - chenhLechTuoi) / 2",
        "tuoiOngHienTai": "(tongTuoiHienTai - chenhLechTuoi) / 2 + chenhLechTuoi",
        "ans": "(((tongTuoiHienTai - chenhLechTuoi) / 2) + chenhLechTuoi - lan * ((tongTuoiHienTai - chenhLechTuoi) / 2)) / (lan - 1)",
        "w1_raw": "tuoiChauHienTai",
        "w2_raw": "tuoiOngHienTai",
        "w3_raw": "ans + 2",
        "w1": "(w1_raw === ans) ? ans + 1 : w1_raw",
        "w2": "(w2_raw === ans || w2_raw === w1) ? (w1 + 1) : w2_raw",
        "w3": "(w3_raw === ans || w3_raw === w1 || w3_raw === w2) ? (w2 + 1) : w3_raw"
      },
      "questionText": "Hiện nay, tổng số tuổi của ông và cháu là {tongTuoiHienTai} tuổi. Ông hơn cháu {chenhLechTuoi} tuổi. Hỏi bao nhiêu năm nữa thì tuổi ông sẽ gấp {lan} lần tuổi cháu?",
      "options": [
        "A. {w1} năm",
        "B. {ans} năm",
        "C. {w2} năm",
        "D. {w3} năm"
      ],
      "correctIndex": 1,
      "hints": [
        "Đầu tiên, hãy tính tuổi hiện tại của ông và cháu. Lưu ý rằng hiệu số tuổi không thay đổi theo thời gian.",
        "Gọi số năm nữa là Y. Thiết lập phương trình theo tuổi ông và cháu sau Y năm, khi đó tuổi ông gấp {lan} lần tuổi cháu."
      ],
      "solutionHtml": "Hiện nay, tuổi của cháu là: ( {tongTuoiHienTai} - {chenhLechTuoi} ) : 2 = {tuoiChauHienTai} (tuổi)<br/><br/>Tuổi của ông hiện nay là: {tuoiChauHienTai} + {chenhLechTuoi} = {tuoiOngHienTai} (tuổi)<br/><br/>Gọi số năm nữa là Y. Khi đó:<br/>Tuổi ông là: {tuoiOngHienTai} + Y (tuổi)<br/>Tuổi cháu là: {tuoiChauHienTai} + Y (tuổi)<br/><br/>Theo đề bài, tuổi ông gấp {lan} lần tuổi cháu, ta có phương trình:<br/>{tuoiOngHienTai} + Y = {lan} x ( {tuoiChauHienTai} + Y )<br/>{tuoiOngHienTai} + Y = {lan} x {tuoiChauHienTai} + {lan} x Y<br/>Chuyển các số hạng có Y sang một vế, các số hạng không có Y sang vế còn lại:<br/>{tuoiOngHienTai} - {lan} x {tuoiChauHienTai} = {lan} x Y - Y<br/>{tuoiOngHienTai} - {lan} x {tuoiChauHienTai} = ( {lan} - 1 ) x Y<br/>Y = ( {tuoiOngHienTai} - {lan} x {tuoiChauHienTai} ) : ( {lan} - 1 )<br/>Y = {ans} (năm)<br/><br/>Vậy, {ans} năm nữa thì tuổi ông sẽ gấp {lan} lần tuổi cháu.<br/>Đáp án đúng là B.",
      "tip": "Dạng toán tuổi thường có một đại lượng không đổi là 'hiệu số tuổi'. Hãy tận dụng điều này để tìm tuổi hiện tại, sau đó thiết lập mối quan hệ tuổi trong tương lai để giải quyết.",
      "level": "chat-luong-cao",
      "type": "l4-kt-c3-d7"
    },
    {
      "isTemplate": true,
      "variables": {
        "spThangTruoc": {
          "min": 1200,
          "max": 1800,
          "step": 100
        },
        "tangThem": {
          "min": 300,
          "max": 600,
          "step": 50
        },
        "giaBan": {
          "min": 50000,
          "max": 80000,
          "step": 5000
        },
        "tongChiPhi": {
          "min": 80000000,
          "max": 120000000,
          "step": 5000000
        }
      },
      "constraints": [
        "( (variables.spThangTruoc + (variables.spThangTruoc + variables.tangThem)) * variables.giaBan ) > (variables.tongChiPhi + 5000000)"
      ],
      "formulas": {
        "spThangNay": "variables.spThangTruoc + variables.tangThem",
        "tongSPHaiThang": "variables.spThangTruoc + formulas.spThangNay",
        "tongTienBan": "formulas.tongSPHaiThang * variables.giaBan",
        "ans": "formulas.tongTienBan - variables.tongChiPhi",
        "w1_goc": "formulas.ans + 1000000",
        "w2_goc": "formulas.ans - 2000000",
        "w3_goc": "formulas.ans + 5000000",
        "w1": "formulas.w1_goc",
        "w2": "(formulas.w2_goc <= 0 || formulas.w2_goc === formulas.w1) ? formulas.ans + 2000000 : formulas.w2_goc",
        "w3": "(formulas.w3_goc === formulas.ans || formulas.w3_goc === formulas.w1 || formulas.w3_goc === formulas.w2) ? formulas.ans + 3000000 : formulas.w3_goc"
      },
      "questionText": "Một xưởng sản xuất đồ chơi. Tháng trước xưởng sản xuất được {spThangTruoc} sản phẩm. Tháng này xưởng sản xuất nhiều hơn tháng trước {tangThem} sản phẩm. Biết mỗi sản phẩm bán với giá {giaBan} đồng và tổng chi phí sản xuất của cả hai tháng là {tongChiPhi} đồng. Hỏi trong hai tháng đó, xưởng lãi bao nhiêu tiền?",
      "options": [
        "{w1} đồng",
        "{ans} đồng",
        "{w2} đồng",
        "{w3} đồng"
      ],
      "correctIndex": 1,
      "hints": [
        "Đầu tiên, hãy tính số sản phẩm xưởng sản xuất được trong tháng này.",
        "Sau đó, tính tổng số sản phẩm mà xưởng sản xuất được trong cả hai tháng.",
        "Tính tổng số tiền thu được từ việc bán tất cả sản phẩm trong hai tháng.",
        "Cuối cùng, tính số tiền lãi bằng cách lấy tổng tiền bán trừ đi tổng chi phí sản xuất."
      ],
      "solutionHtml": "Số sản phẩm xưởng sản xuất được trong tháng này là:<br/>{spThangTruoc} + {tangThem} = {spThangNay} (sản phẩm)<br/><br/>Tổng số sản phẩm xưởng sản xuất được trong cả hai tháng là:<br/>{spThangTruoc} + {spThangNay} = {tongSPHaiThang} (sản phẩm)<br/><br/>Tổng số tiền thu được từ việc bán tất cả sản phẩm trong hai tháng là:<br/>{tongSPHaiThang} $\\times$ {giaBan} = {tongTienBan} (đồng)<br/><br/>Số tiền lãi của xưởng trong hai tháng là:<br/>{tongTienBan} $-$ {tongChiPhi} = {ans} (đồng)<br/><br/>Đáp án đúng là {ans} đồng.",
      "tip": "Để tính lãi, ta luôn lấy tổng tiền thu được trừ đi tổng chi phí. Hãy chắc chắn rằng bạn đã tính toán đầy đủ số lượng sản phẩm và doanh thu cho toàn bộ thời gian được hỏi.",
      "level": "chat-luong-cao",
      "type": "l4-kt-c3-d8"
    },
    {
      "isTemplate": true,
      "variables": {
        "soHocSinh": {
          "min": 800,
          "max": 1200,
          "step": 50
        },
        "phanSoMau": {
          "min": 10,
          "max": 15,
          "step": 1
        },
        "phanSoMauCB": {
          "min": 2,
          "max": 5,
          "step": 1
        }
      },
      "constraints": [
        "soHocSinh % phanSoMau === 0",
        "(soHocSinh / phanSoMau) % phanSoMauCB === 0"
      ],
      "formulas": {
        "soGiaoVien": "soHocSinh / phanSoMau",
        "soCanBo": "(soHocSinh / phanSoMau) / phanSoMauCB",
        "ans": "soHocSinh + (soHocSinh / phanSoMau) + ((soHocSinh / phanSoMau) / phanSoMauCB)",
        "w1_goc": "soHocSinh + soGiaoVien",
        "w2_goc": "soHocSinh + soCanBo",
        "w3_goc": "soGiaoVien + soCanBo",
        "w1": "(w1_goc === ans) ? ans + 5 : w1_goc",
        "w2": "(w2_goc === ans || w2_goc === w1) ? (ans + 7) : w2_goc",
        "w3": "(w3_goc === ans || w3_goc === w1 || w3_goc === w2) ? (ans + 12) : w3_goc"
      },
      "questionText": "Một trường học có {soHocSinh} học sinh. Số giáo viên bằng 1/{phanSoMau} số học sinh. Số cán bộ quản lý bằng 1/{phanSoMauCB} số giáo viên. Hỏi tổng số người (gồm học sinh, giáo viên và cán bộ quản lý) của trường đó là bao nhiêu?",
      "options": [
        "{w1} người",
        "{ans} người",
        "{w2} người",
        "{w3} người"
      ],
      "correctIndex": 1,
      "hints": [
        "Tính số lượng giáo viên bằng cách lấy {soHocSinh} chia cho {phanSoMau}.",
        "Tính số lượng cán bộ quản lý bằng cách lấy số giáo viên vừa tìm được chia cho {phanSoMauCB}.",
        "Cộng số học sinh, số giáo viên và số cán bộ quản lý lại để được tổng số người."
      ],
      "solutionHtml": "Số lượng giáo viên của trường là: {soHocSinh} : {phanSoMau} = {soGiaoVien} (người).<br/><br/>Số lượng cán bộ quản lý của trường là: {soGiaoVien} : {phanSoMauCB} = {soCanBo} (người).<br/><br/>Tổng số người của trường là: {soHocSinh} + {soGiaoVien} + {soCanBo} = {ans} (người).<br/><br/>Đáp án đúng là {ans} người.",
      "tip": "Khi bài toán cho các đại lượng liên quan theo dạng phân số, hãy thực hiện phép chia để tìm giá trị của mỗi nhóm, sau đó cộng tất cả lại.",
      "level": "chat-luong-cao",
      "type": "l4-kt-c3-d9"
    },
    {
      "isTemplate": true,
      "variables": {
        "tongSoKhach": {
          "min": 250,
          "max": 400,
          "step": 10
        },
        "sucChuaXe": {
          "min": 30,
          "max": 50,
          "step": 5
        },
        "chiPhiMoiXe": {
          "min": 1500000,
          "max": 2500000,
          "step": 100000
        }
      },
      "constraints": [
        "tongSoKhach % sucChuaXe != 0"
      ],
      "formulas": {
        "soChuyenXeFull": "Math.floor(tongSoKhach / sucChuaXe)",
        "soKhachLe": "tongSoKhach % sucChuaXe",
        "tongSoChuyenXe": "Math.floor(tongSoKhach / sucChuaXe) + 1",
        "ans": "(Math.floor(tongSoKhach / sucChuaXe) + 1) * chiPhiMoiXe",
        "w1_goc": "Math.floor(tongSoKhach / sucChuaXe) * chiPhiMoiXe",
        "w2_goc": "tongSoKhach * 10000",
        "w3_goc": "(Math.floor(tongSoKhach / sucChuaXe) + 2) * chiPhiMoiXe",
        "w1": "(w1_goc === ans) ? ans + chiPhiMoiXe : w1_goc",
        "w2": "(w2_goc === ans || w2_goc === w1) ? ans + 2 * chiPhiMoiXe : w2_goc",
        "w3": "(w3_goc === ans || w3_goc === w1 || w3_goc === w2) ? ans + 3 * chiPhiMoiXe : w3_goc"
      },
      "questionText": "Một công ty du lịch tổ chức chuyến đi tham quan cho {tongSoKhach} khách. Mỗi xe buýt có sức chứa {sucChuaXe} người. Chi phí xăng xe cho mỗi chuyến xe buýt là {chiPhiMoiXe} đồng. Hỏi tổng số tiền công ty phải chi trả cho chi phí xăng xe của chuyến đi là bao nhiêu?",
      "options": [
        "A. {w1} đồng",
        "B. {ans} đồng",
        "C. {w2} đồng",
        "D. {w3} đồng"
      ],
      "correctIndex": 1,
      "hints": [
        "Đầu tiên, hãy tính số xe buýt cần dùng để chở hết {tongSoKhach} khách. Vì {soKhachLe} khách còn lẻ ra nên cần thêm 1 chuyến xe nữa.",
        "Sau đó, lấy tổng số chuyến xe nhân với chi phí xăng xe mỗi chuyến."
      ],
      "solutionHtml": "Số chuyến xe buýt cần dùng để chở hết {tongSoKhach} khách là:<br/>{tongSoKhach} chia {sucChuaXe} được {soChuyenXeFull} chuyến và dư {soKhachLe} người.<br/><br/>Vì {soKhachLe} người còn lại vẫn cần được chở đi, nên ta cần thêm 1 chuyến xe nữa.<br/>Vậy tổng số chuyến xe buýt cần là: {soChuyenXeFull} + 1 = {tongSoChuyenXe} chuyến.<br/><br/>Tổng số tiền công ty phải chi trả là:<br/>{tongSoChuyenXe} nhân {chiPhiMoiXe} = {ans} đồng.<br/><br/>Đáp án đúng là B.",
      "tip": "Khi tính số lượng xe, hộp, nhóm,... mà có phần dư, luôn nhớ phải làm tròn lên (thêm một đơn vị) nếu có bất kỳ phần dư nào để đảm bảo tất cả đều được vận chuyển.",
      "level": "chat-luong-cao",
      "type": "l4-kt-c3-d10"
    },
    {
      "isTemplate": true,
      "variables": {
        "thung1": {
          "min": 1500,
          "max": 2000,
          "step": 100
        },
        "themThung2": {
          "min": 300,
          "max": 600,
          "step": 50
        },
        "gapThung3": {
          "min": 2,
          "max": 4,
          "step": 1
        },
        "giamThung4": {
          "min": 50,
          "max": 150,
          "step": 10
        }
      },
      "constraints": [
        "thung1 + themThung2 > giamThung4 + 100",
        "(thung1 + themThung2) * gapThung3 > giamThung4"
      ],
      "formulas": {
        "thung2": "thung1 + themThung2",
        "thung3": "(thung1 + themThung2) * gapThung3",
        "thung4": "(thung1 + themThung2) * gapThung3 - giamThung4",
        "ans": "thung1 + (thung1 + themThung2) + ((thung1 + themThung2) * gapThung3) + ((thung1 + themThung2) * gapThung3 - giamThung4)",
        "w1_goc": "thung1 + (thung1 + themThung2)",
        "w2_goc": "thung1 + (thung1 + themThung2) + ((thung1 + themThung2) * gapThung3)",
        "w3_goc": "thung2 + thung3 + thung4",
        "w1": "(w1_goc === ans) ? ans + 100 : w1_goc",
        "w2": "(w2_goc === ans || w2_goc === w1) ? ans + 200 : w2_goc",
        "w3": "(w3_goc === ans || w3_goc === w1 || w3_goc === w2) ? ans + 300 : w3_goc"
      },
      "questionText": "Một nhà máy có 4 thùng hàng. Thùng thứ nhất chứa {thung1} sản phẩm. Thùng thứ hai chứa nhiều hơn thùng thứ nhất {themThung2} sản phẩm. Thùng thứ ba chứa số sản phẩm gấp {gapThung3} lần thùng thứ hai. Thùng thứ tư chứa ít hơn thùng thứ ba {giamThung4} sản phẩm. Hỏi cả bốn thùng hàng đó chứa tổng cộng bao nhiêu sản phẩm?",
      "options": [
        "A. {w1} sản phẩm",
        "B. {ans} sản phẩm",
        "C. {w2} sản phẩm",
        "D. {w3} sản phẩm"
      ],
      "correctIndex": 1,
      "hints": [
        "Tính số sản phẩm ở thùng thứ hai bằng cách lấy số sản phẩm thùng thứ nhất cộng với {themThung2}.",
        "Tính số sản phẩm ở thùng thứ ba bằng cách lấy số sản phẩm thùng thứ hai nhân với {gapThung3}.",
        "Tính số sản phẩm ở thùng thứ tư bằng cách lấy số sản phẩm thùng thứ ba trừ đi {giamThung4}.",
        "Tính tổng số sản phẩm của cả bốn thùng bằng cách cộng kết quả của bốn thùng lại."
      ],
      "solutionHtml": "Số sản phẩm ở thùng thứ hai là:<br/>{thung1} + {themThung2} = {thung2} (sản phẩm)<br/><br/>Số sản phẩm ở thùng thứ ba là:<br/>{thung2} × {gapThung3} = {thung3} (sản phẩm)<br/><br/>Số sản phẩm ở thùng thứ tư là:<br/>{thung3} - {giamThung4} = {thung4} (sản phẩm)<br/><br/>Tổng số sản phẩm cả bốn thùng hàng chứa là:<br/>{thung1} + {thung2} + {thung3} + {thung4} = {ans} (sản phẩm)<br/><br/>Đáp án đúng là B: {ans} sản phẩm.",
      "tip": "Khi giải các bài toán có nhiều đối tượng, hãy xác định rõ ràng từng bước tính toán. Bắt đầu từ đại lượng đã biết và lần lượt tính các đại lượng liên quan theo thứ tự thùng 2, thùng 3, thùng 4, sau đó cộng tổng.",
      "level": "chat-luong-cao",
      "type": "l4-kt-c3-d11"
    },
    {
      "isTemplate": true,
      "variables": {
        "thanhPhoA": {
          "min": 3000000,
          "max": 5000000,
          "step": 100000
        },
        "honThanhPhoB": {
          "min": 800000,
          "max": 1500000,
          "step": 100000
        },
        "gapThanhPhoC": {
          "min": 2,
          "max": 3,
          "step": 1
        }
      },
      "constraints": [
        "thanhPhoA > honThanhPhoB",
        "thanhPhoA % gapThanhPhoC === 0"
      ],
      "formulas": {
        "thanhPhoB": "thanhPhoA - honThanhPhoB",
        "thanhPhoC": "thanhPhoA / gapThanhPhoC",
        "ans": "thanhPhoA + (thanhPhoA - honThanhPhoB) + (thanhPhoA / gapThanhPhoC)",
        "w1_raw": "thanhPhoA + (thanhPhoA - honThanhPhoB)",
        "w2_raw": "thanhPhoA + (thanhPhoA / gapThanhPhoC)",
        "w3_raw": "(thanhPhoA - honThanhPhoB) + (thanhPhoA / gapThanhPhoC)",
        "w1": "(w1_raw === ans) ? ans + 100000 : w1_raw",
        "w2": "(w2_raw === ans || w2_raw === w1) ? ans + 200000 : w2_raw",
        "w3": "(w3_raw === ans || w3_raw === w1 || w3_raw === w2) ? ans + 300000 : w3_raw"
      },
      "questionText": "Dân số của thành phố A là {thanhPhoA} người. Dân số thành phố B ít hơn thành phố A là {honThanhPhoB} người. Dân số thành phố A gấp {gapThanhPhoC} lần dân số thành phố C. Hỏi tổng dân số của cả ba thành phố A, B và C là bao nhiêu người?",
      "options": [
        "A. {w1} người",
        "B. {ans} người",
        "C. {w2} người",
        "D. {w3} người"
      ],
      "correctIndex": 1,
      "hints": [
        "Tính dân số thành phố B bằng cách lấy dân số A trừ đi số người ít hơn.",
        "Tính dân số thành phố C bằng cách lấy dân số A chia cho số lần.",
        "Cộng dân số của cả ba thành phố lại để ra đáp án cuối cùng."
      ],
      "solutionHtml": "Dân số của thành phố B là:<br/>{thanhPhoA} - {honThanhPhoB} = {thanhPhoB} (người)<br/><br/>Dân số của thành phố C là:<br/>{thanhPhoA} : {gapThanhPhoC} = {thanhPhoC} (người)<br/><br/>Tổng dân số của cả ba thành phố A, B và C là:<br/>{thanhPhoA} + {thanhPhoB} + {thanhPhoC} = {ans} (người)<br/><br/>Đáp án đúng là {ans} người.",
      "tip": "Phân tích kỹ mối quan hệ giữa các đại lượng. Ít hơn là phép trừ, gấp N lần là phép nhân, do đó khi biết số gấp N lần để tìm số còn lại ta dùng phép chia.",
      "level": "chat-luong-cao",
      "type": "l4-kt-c3-d12"
    },
    {
      "isTemplate": true,
      "variables": {
        "lan1": {
          "min": 800,
          "max": 1200,
          "step": 50
        },
        "kemLan2": {
          "min": 100,
          "max": 300,
          "step": 20
        },
        "gapLan3": {
          "min": 2,
          "max": 4,
          "step": 1
        },
        "moiLan": {
          "min": 3,
          "max": 5,
          "step": 1
        }
      },
      "constraints": [
        "variables.lan1 > variables.kemLan2 + 100",
        "(variables.lan1 - variables.kemLan2) * variables.gapLan3 % variables.moiLan === 0",
        "variables.lan1 % variables.moiLan === 0",
        "variables.moiLan > 1"
      ],
      "formulas": {
        "lan2": "variables.lan1 - variables.kemLan2",
        "lan3": "(variables.lan1 - variables.kemLan2) * variables.gapLan3",
        "ans": "((variables.lan1 - variables.kemLan2) * variables.gapLan3) / variables.moiLan",
        "w1_goc": "(variables.lan1 - variables.kemLan2) * variables.gapLan3",
        "w1": "(w1_goc === ans) ? ans + 10 : w1_goc",
        "w2_goc": "variables.lan1 / variables.moiLan",
        "w2": "(w2_goc === ans || w2_goc === w1) ? ans + 20 : w2_goc",
        "w3_goc": "variables.lan3 + variables.moiLan",
        "w3": "(w3_goc === ans || w3_goc === w1 || w3_goc === w2) ? ans + 30 : w3_goc"
      },
      "questionText": "Một nhà xuất bản in sách trong ba đợt. Đợt 1 in được {lan1} quyển sách. Đợt 2 in ít hơn đợt 1 là {kemLan2} quyển. Đợt 3 in số quyển sách gấp {gapLan3} lần số sách của đợt 2. Hỏi nếu số sách của đợt 3 được chia đều thành {moiLan} phần bằng nhau thì mỗi phần có bao nhiêu quyển sách?",
      "options": [
        "A. {w1} quyển",
        "B. {ans} quyển",
        "C. {w2} quyển",
        "D. {w3} quyển"
      ],
      "correctIndex": 1,
      "hints": [
        "Tính số sách in được ở đợt 2 bằng cách lấy số sách đợt 1 trừ đi {kemLan2}.",
        "Tính số sách in được ở đợt 3 bằng cách lấy số sách đợt 2 nhân với {gapLan3}.",
        "Lấy số sách của đợt 3 chia đều cho {moiLan} phần."
      ],
      "solutionHtml": "Số sách in được ở đợt 2 là:<br/>{lan1} - {kemLan2} = {lan2} (quyển)<br/><br/>Số sách in được ở đợt 3 là:<br/>{lan2} × {gapLan3} = {lan3} (quyển)<br/><br/>Nếu số sách của đợt 3 được chia đều thành {moiLan} phần bằng nhau thì mỗi phần có số quyển sách là:<br/>{lan3} : {moiLan} = {ans} (quyển)<br/><br/>Đáp án đúng là B.",
      "tip": "Đọc kỹ câu hỏi cuối cùng để biết cần tìm đại lượng nào. Đừng dừng lại ở các bước trung gian nếu đó chưa phải là câu trả lời cuối cùng mà đề bài yêu cầu.",
      "level": "chat-luong-cao",
      "type": "l4-kt-c3-d13"
    }
  ]
}